kaizen_cyber_lib/__init__.py
kaizen_cyber_lib/account_checker.py
kaizen_cyber_lib/alert_tools.py
kaizen_cyber_lib/api_bruteforce.py
kaizen_cyber_lib/bruteforce_tools.py
kaizen_cyber_lib/crypto_tools.py
kaizen_cyber_lib/ddos_tools.py
kaizen_cyber_lib/domain_tools.py
kaizen_cyber_lib/social_media_finder.py
kaizen_cyber_lib/traffic_monitor.py
KaizenCyberLib-1.0.0.dist-info/METADATA
KaizenCyberLib-1.0.0.dist-info/WHEEL
KaizenCyberLib-1.0.0.dist-info/top_level.txt
KaizenCyberLib-1.0.0.dist-info/RECORD
