Metadata-Version: 2.2
Name: KaizenCyberLib
Version: 1.0.0
Summary: Une bibliothèque Python pour la cybersécurité et les tests éthiques.
Home-page: https://github.com/votre_github/KaizenCyberLib
Author: Votre Nom
Author-email: votre.email@example.com
License: MIT
Classifier: Programming Language :: Python :: 3
Classifier: License :: OSI Approved :: MIT License
Classifier: Operating System :: OS Independent
Classifier: Topic :: Security
Classifier: Development Status :: 4 - Beta
Classifier: Intended Audience :: Developers
Requires-Python: >=3.7
Requires-Dist: requests
Requires-Dist: scapy
Requires-Dist: pytest
Requires-Dist: pytest-mock
Requires-Dist: whois
Dynamic: author
Dynamic: author-email
Dynamic: classifier
Dynamic: description
Dynamic: description-content-type
Dynamic: home-page
Dynamic: license
Dynamic: requires-dist
Dynamic: requires-python
Dynamic: summary
